LICENSE
MANIFEST.in
README.rst
setup.py
argparse_plus/__init__.py
argparse_plus/argparse_plus.py
argparse_plus.egg-info/PKG-INFO
argparse_plus.egg-info/SOURCES.txt
argparse_plus.egg-info/dependency_links.txt
argparse_plus.egg-info/top_level.txt